hdfs_native-0.13.3.dist-info/METADATA
hdfs_native-0.13.3.dist-info/WHEEL
hdfs_native-0.13.3.dist-info/entry_points.txt
hdfs_native/__init__.py
hdfs_native/_internal.abi3.so
hdfs_native/_internal.pyi
hdfs_native/cli.py
hdfs_native/fsspec.py
hdfs_native/py.typed
hdfs_native-0.13.3.dist-info/RECORD
