Metadata-Version: 2.4
Name: hdfs-native
Version: 0.13.3
Classifier: Programming Language :: Rust
Classifier: Programming Language :: Python :: Implementation :: CPython
Classifier: Programming Language :: Python :: Implementation :: PyPy
Requires-Dist: argcomplete>=3.0.0
Requires-Dist: typing-extensions
Requires-Dist: fsspec
Summary: Python bindings for hdfs-native Rust library
Home-Page: https://github.com/Kimahriman/hdfs-native
Requires-Python: >=3.10
Project-URL: repository, https://github.com/Kimahriman/hdfs-native
Project-URL: documentation, https://hdfs-native.readthedocs.io/
